ppgan/__init__.py
ppgan/version.py
ppgan/apps/__init__.py
ppgan/apps/animegan_predictor.py
ppgan/apps/base_predictor.py
ppgan/apps/dain_predictor.py
ppgan/apps/deepremaster_predictor.py
ppgan/apps/deoldify_predictor.py
ppgan/apps/edvr_predictor.py
ppgan/apps/face_parse_predictor.py
ppgan/apps/first_order_predictor.py
ppgan/apps/lapstyle_predictor.py
ppgan/apps/midas_predictor.py
ppgan/apps/mpr_predictor.py
ppgan/apps/photo2cartoon_predictor.py
ppgan/apps/photopen_predictor.py
ppgan/apps/pixel2style2pixel_predictor.py
ppgan/apps/psgan_predictor.py
ppgan/apps/realsr_predictor.py
ppgan/apps/recurrent_vsr_predictor.py
ppgan/apps/styleganv2_predictor.py
ppgan/apps/styleganv2editing_predictor.py
ppgan/apps/styleganv2fitting_predictor.py
ppgan/apps/styleganv2mixing_predictor.py
ppgan/apps/wav2lip_predictor.py
ppgan/apps/midas/README.md
ppgan/apps/midas/__init__.py
ppgan/apps/midas/blocks.py
ppgan/apps/midas/midas_net.py
ppgan/apps/midas/resnext.py
ppgan/apps/midas/transforms.py
ppgan/apps/midas/utils.py
ppgan/datasets/__init__.py
ppgan/datasets/animeganv2_dataset.py
ppgan/datasets/base_dataset.py
ppgan/datasets/base_sr_dataset.py
ppgan/datasets/builder.py
ppgan/datasets/common_vision_dataset.py
ppgan/datasets/edvr_dataset.py
ppgan/datasets/firstorder_dataset.py
ppgan/datasets/image_folder.py
ppgan/datasets/lapstyle_dataset.py
ppgan/datasets/makeup_dataset.py
ppgan/datasets/mpr_dataset.py
ppgan/datasets/paired_dataset.py
ppgan/datasets/photopen_dataset.py
ppgan/datasets/repeat_dataset.py
ppgan/datasets/single_dataset.py
ppgan/datasets/sr_reds_multiple_gt_dataset.py
ppgan/datasets/starganv2_dataset.py
ppgan/datasets/unpaired_dataset.py
ppgan/datasets/vsr_folder_dataset.py
ppgan/datasets/vsr_vimeo90k_dataset.py
ppgan/datasets/wav2lip_dataset.py
ppgan/datasets/preprocess/__init__.py
ppgan/datasets/preprocess/builder.py
ppgan/datasets/preprocess/io.py
ppgan/datasets/preprocess/transforms.py
ppgan/engine/__init__.py
ppgan/engine/trainer.py
ppgan/faceutils/__init__.py
ppgan-2.1.0.dist-info/LICENSE
ppgan-2.1.0.dist-info/METADATA
ppgan-2.1.0.dist-info/WHEEL
ppgan-2.1.0.dist-info/entry_points.txt
ppgan-2.1.0.dist-info/top_level.txt
ppgan-2.1.0.dist-info/RECORD
