Metadata-Version: 2.1
Name: ppgan
Version: 2.1.0
Summary: Awesome GAN toolkits based on PaddlePaddle
Home-page: https://github.com/PaddlePaddle/PaddleGAN
Author: PaddlePaddle Author
License: Apache License 2.0
Download-URL: https://github.com/PaddlePaddle/PaddleGAN.git
Keywords: gan paddlegan
Platform: UNKNOWN
Classifier: Intended Audience :: Developers
Classifier: Operating System :: OS Independent
Classifier: Natural Language :: Chinese (Simplified)
Classifier: Programming Language :: Python :: 3
Classifier: Programming Language :: Python :: 3.5
Classifier: Programming Language :: Python :: 3.6
Classifier: Programming Language :: Python :: 3.7
Classifier: Topic :: Utilities
Requires-Dist: tqdm
Requires-Dist: PyYAML (>=5.1)
Requires-Dist: scikit-image (>=0.14.0)
Requires-Dist: scipy (>=1.1.0)
Requires-Dist: opencv-python
Requires-Dist: imageio (==2.9.0)
Requires-Dist: imageio-ffmpeg
Requires-Dist: librosa (==0.8.1)
Requires-Dist: numba (==0.53.1)
Requires-Dist: easydict
Requires-Dist: munch
Requires-Dist: natsort
Requires-Dist: matplotlib
